GetArgs/GetTweet.py
GetArgs/__init__.py
GetArgs/__main__.py
GetArgs/test_GetTweet.py
GetArgs/ManagingArgs/Adding_Simple.py
GetArgs/ManagingArgs/Criteria.py
GetArgs/ManagingArgs/__init__.py
SimpleGetArgs-0.0.3.dist-info/LICENSE.txt
SimpleGetArgs-0.0.3.dist-info/METADATA
SimpleGetArgs-0.0.3.dist-info/WHEEL
SimpleGetArgs-0.0.3.dist-info/entry_points.txt
SimpleGetArgs-0.0.3.dist-info/top_level.txt
SimpleGetArgs-0.0.3.dist-info/RECORD
