Metadata-Version: 2.1
Name: SimpleGetArgs
Version: 0.0.3
Summary: Test to Publish the Command Line
Home-page: https://github.com/MSBeni/PublishArgparse
Author: MSBeni
Author-email: andrei.sokurov.bitco@gmail.com
License: UNKNOWN
Keywords: calculator
Platform: UNKNOWN
Classifier: Development Status :: 5 - Production/Stable
Classifier: Environment :: Console
Classifier: Environment :: Web Environment
Classifier: Intended Audience :: End Users/Desktop
Classifier: Intended Audience :: System Administrators
Classifier: License :: OSI Approved :: MIT License
Classifier: Operating System :: MacOS :: MacOS X
Classifier: Operating System :: Microsoft :: Windows
Classifier: Programming Language :: Python :: 3
Classifier: Topic :: Communications :: Email
Classifier: Topic :: Office/Business
Classifier: Topic :: Software Development :: Bug Tracking
Provides-Extra: dev
Requires-Dist: pytest (>=3.7) ; extra == 'dev'
